pygayme/__init__.py
pygayme-1.1.0.dist-info/METADATA
pygayme-1.1.0.dist-info/WHEEL
pygayme-1.1.0.dist-info/top_level.txt
pygayme-1.1.0.dist-info/RECORD
