Metadata-Version: 2.1
Name: pygayme
Version: 1.1.0
Summary: pygayme
Author: mr.r
Classifier: Programming Language :: Python :: 3
Classifier: License :: OSI Approved :: MIT License
Classifier: Operating System :: OS Independent
Requires-Dist: pygame-ce
